porgo/__init__.py
porgo/_typing.py
porgo/_version.py
porgo/runtime.py
porgo-1.1.1.dist-info/LICENSE
porgo-1.1.1.dist-info/METADATA
porgo-1.1.1.dist-info/WHEEL
porgo-1.1.1.dist-info/top_level.txt
porgo-1.1.1.dist-info/RECORD
