Metadata-Version: 2.1
Name: porgo
Version: 1.1.1
Summary: The portable universal library in global optimization.
Home-page: https://github.com/linjing-lab/porgo
Download-URL: https://github.com/linjing-lab/porgo/tags
Author: 林景
Author-email: linjing010729@163.com
License: MIT
Project-URL: Source, https://github.com/linjing-lab/porgo/tree/main/porgo/
Project-URL: Tracker, https://github.com/linjing-lab/porgo/issues
Classifier: Development Status :: 5 - Production/Stable
Classifier: Intended Audience :: Developers
Classifier: Intended Audience :: Education
Classifier: Intended Audience :: Science/Research
Classifier: Programming Language :: Python :: 3.7
Classifier: Programming Language :: Python :: 3.8
Classifier: Programming Language :: Python :: 3.9
Classifier: Programming Language :: Python :: 3.10
Classifier: Programming Language :: Python :: 3.11
Classifier: Programming Language :: Python :: 3.12
Classifier: License :: OSI Approved :: MIT License
Classifier: Topic :: Scientific/Engineering
Classifier: Topic :: Scientific/Engineering :: Mathematics
Classifier: Topic :: Software Development
Classifier: Topic :: Software Development :: Libraries
Classifier: Topic :: Software Development :: Libraries :: Python Modules
License-File: LICENSE
Requires-Dist: numpy (>=1.21.0)
